linter_adapters/__init__.py
linter_adapters/common.py
linter_adapters/parser.py
linter_adapters/types.py
linter_adapters/integrations/__init__.py
linter_adapters/integrations/checkers/__init__.py
linter_adapters/integrations/checkers/flake8_bandit.py
linter_adapters/integrations/checkers/flake8_bugbear.py
linter_adapters/integrations/checkers/flake8_class_c.py
linter_adapters/integrations/checkers/flake8_docstrings.py
linter_adapters/integrations/checkers/flake8_oneliners.py
linter_adapters/integrations/checkers/flake8_rst.py
linter_adapters/integrations/checkers/flake8_string_format.py
linter_adapters/integrations/checkers/pycodestyle.py
linter_adapters/integrations/checkers/pyflakes.py
linter_adapters/integrations/checkers/wemake_python_styleguide.py
linter_adapters/integrations/formatters/__init__.py
linter_adapters/integrations/formatters/flake8_as_pylint_json.py
linter_adapters/integrations/formatters/flake8_for_pycharm.py
linter_adapters/integrations/formatters/pylint.py
linter_adapters-0.1.2.dist-info/licenses/LICENSE.txt
linter_adapters-0.1.2.dist-info/METADATA
linter_adapters-0.1.2.dist-info/WHEEL
linter_adapters-0.1.2.dist-info/entry_points.txt
linter_adapters-0.1.2.dist-info/top_level.txt
linter_adapters-0.1.2.dist-info/RECORD
