Metadata-Version: 2.4
Name: linter-adapters
Version: 0.1.2
Summary: An adapter which provides categorization & descriptions on popular linters & checkers
Home-page: https://gitlab.com/Hares-Lab/tools/linter-adapters
Author: Peter Zaitcev
Maintainer: Peter Zaitcev
License: BSD 2-clause license
Classifier: Development Status :: 2 - Pre-Alpha
Classifier: Intended Audience :: Developers
Classifier: Natural Language :: English
Classifier: Operating System :: OS Independent
Classifier: Framework :: Flake8
Classifier: Programming Language :: Python :: 3.10
Classifier: Programming Language :: Python :: 3.11
Classifier: Programming Language :: Python :: 3.12
Classifier: Programming Language :: Python :: 3.13
Requires-Python: >=3.10
License-File: LICENSE.txt
Provides-Extra: linters
Requires-Dist: flake8; extra == "linters"
Provides-Extra: supported-plugins
Requires-Dist: flake8-bandit; extra == "supported-plugins"
Requires-Dist: flake8-broken-line; extra == "supported-plugins"
Requires-Dist: flake8-bugbear; extra == "supported-plugins"
Requires-Dist: flake8-commas; extra == "supported-plugins"
Requires-Dist: flake8-comprehensions; extra == "supported-plugins"
Requires-Dist: flake8-datetimez; extra == "supported-plugins"
Requires-Dist: flake8-debugger; extra == "supported-plugins"
Requires-Dist: flake8-docstrings; extra == "supported-plugins"
Requires-Dist: flake8-eradicate; extra == "supported-plugins"
Requires-Dist: flake8-isort; extra == "supported-plugins"
Requires-Dist: flake8-quotes; extra == "supported-plugins"
Requires-Dist: flake8-rst-docstrings; extra == "supported-plugins"
Requires-Dist: flake8-string-format; extra == "supported-plugins"
Requires-Dist: wemake-python-styleguide; extra == "supported-plugins"
Provides-Extra: test
Requires-Dist: wheel; extra == "test"
Requires-Dist: lxml; extra == "test"
Requires-Dist: unittest-xml-reporting; extra == "test"
Provides-Extra: all
Requires-Dist: flake8; extra == "all"
Requires-Dist: flake8-bandit; extra == "all"
Requires-Dist: flake8-broken-line; extra == "all"
Requires-Dist: flake8-bugbear; extra == "all"
Requires-Dist: flake8-commas; extra == "all"
Requires-Dist: flake8-comprehensions; extra == "all"
Requires-Dist: flake8-datetimez; extra == "all"
Requires-Dist: flake8-debugger; extra == "all"
Requires-Dist: flake8-docstrings; extra == "all"
Requires-Dist: flake8-eradicate; extra == "all"
Requires-Dist: flake8-isort; extra == "all"
Requires-Dist: flake8-quotes; extra == "all"
Requires-Dist: flake8-rst-docstrings; extra == "all"
Requires-Dist: flake8-string-format; extra == "all"
Requires-Dist: wemake-python-styleguide; extra == "all"
Requires-Dist: wheel; extra == "all"
Requires-Dist: lxml; extra == "all"
Requires-Dist: unittest-xml-reporting; extra == "all"
Dynamic: author
Dynamic: classifier
Dynamic: description
Dynamic: description-content-type
Dynamic: home-page
Dynamic: license
Dynamic: license-file
Dynamic: maintainer
Dynamic: provides-extra
Dynamic: requires-python
Dynamic: summary
